src/__init__.py
src/commands.py
src/config.py
src/constants.py
src/es_wrapper.py
src/migrate.py
src/templates/chalan.ini.mako
src/templates/script.py.mako
src/utils/__init__.py
src/utils/exceptions.py
chalan-0.1.4.dist-info/LICENSE
chalan-0.1.4.dist-info/METADATA
chalan-0.1.4.dist-info/WHEEL
chalan-0.1.4.dist-info/entry_points.txt
chalan-0.1.4.dist-info/top_level.txt
chalan-0.1.4.dist-info/RECORD
